MANIFEST.in
README.md
requirements.txt
setup.py
exoclock/__author__.txt
exoclock/__author_email__.txt
exoclock/__databases__.pickle
exoclock/__databases_setup__.py
exoclock/__description__.txt
exoclock/__init__.py
exoclock/__url__.txt
exoclock/__version__.txt
exoclock/databases.py
exoclock/errors.py
exoclock.egg-info/PKG-INFO
exoclock.egg-info/SOURCES.txt
exoclock.egg-info/dependency_links.txt
exoclock.egg-info/not-zip-safe
exoclock.egg-info/requires.txt
exoclock.egg-info/top_level.txt
exoclock/catalogues/__init__.py
exoclock/catalogues/catalogues.py
exoclock/catalogues/simbad.py
exoclock/processes/__init__.py
exoclock/processes/files.py
exoclock/spacetime/__init__.py
exoclock/spacetime/angles.py
exoclock/spacetime/moments.py
exoclock/spacetime/observatories.py
exoclock/spacetime/targets.py
tests/test_catalogues.py
tests/test_spacetime_angles.py
tests/test_spacetime_moments.py
tests/test_spacetime_observatories.py
tests/test_specetime_targets.py
tests/test_tools.py